baskerville-0.3.0.dist-info/METADATA
baskerville-0.3.0.dist-info/WHEEL
baskerville-0.3.0.dist-info/license_files/LICENSE
baskerville/__init__.py
baskerville/baskerville.abi3.so
baskerville-0.3.0.dist-info/RECORD
